pymop/__init__.py
pymop/factory.py
pymop/gradient.py
pymop/plot.py
pymop/problem.py
pymop/util.py
pymop/pf/kursawe.pf
pymop/pf/osy.pf
pymop/pf/tnk.pf
pymop/pf/welded_beam.pf
pymop/problems/__init__.py
pymop/problems/ackley.py
pymop/problems/bnh.py
pymop/problems/cantilevered_beam.py
pymop/problems/carside.py
pymop/problems/cdtlz.py
pymop/problems/ctp.py
pymop/problems/dtlz.py
pymop/problems/g.py
pymop/problems/griewank.py
pymop/problems/himmelblau.py
pymop/problems/knapsack.py
pymop/problems/kursawe.py
pymop/problems/osy.py
pymop/problems/pressure_vessel.py
pymop/problems/rastrigin.py
pymop/problems/rosenbrock.py
pymop/problems/schwefel.py
pymop/problems/sphere.py
pymop/problems/tnk.py
pymop/problems/truss2d.py
pymop/problems/welded_beam.py
pymop/problems/zakharov.py
pymop/problems/zdt.py
pymop/usage/__init__.py
pymop/usage/calc_pareto_front.py
pymop/usage/define_custom_problem.py
pymop/usage/define_custom_problem_with_gradient.py
pymop/usage/evaluate_problem.py
pymop/usage/evaluate_problem_with_gradients.py
pymop/usage/get_problem_from_function.py
pymop/usage/get_problem_from_string.py
pymop-0.2.4.dist-info/METADATA
pymop-0.2.4.dist-info/RECORD
pymop-0.2.4.dist-info/WHEEL
pymop-0.2.4.dist-info/top_level.txt
