Metadata-Version: 1.0
Name: pymop
Version: 0.2.4
Summary: Multi-Objective Optimization Problems
Home-page: https://github.com/msu-coinlab/pymop
Author: Julian Blank
Author-email: blankjul@egr.msu.edu
License: Apache License 2.0
Keywords: optimization
Platform: any
